README.rst
setup.cfg
setup.py
requests_aws4auth/__init__.py
requests_aws4auth/aws4auth.py
requests_aws4auth/aws4signingkey.py
requests_aws4auth/exceptions.py
requests_aws4auth/six.py
requests_aws4auth/../HISTORY.rst
requests_aws4auth/../LICENSE
requests_aws4auth/../NOTICE
requests_aws4auth/../README.rst
requests_aws4auth/test/requests_aws4auth_test.py
requests_aws4auth_redux.egg-info/PKG-INFO
requests_aws4auth_redux.egg-info/SOURCES.txt
requests_aws4auth_redux.egg-info/dependency_links.txt
requests_aws4auth_redux.egg-info/requires.txt
requests_aws4auth_redux.egg-info/top_level.txt