Metadata-Version: 1.1
Name: requests-aws4auth-redux
Version: 0.40
Summary: AWS4 authentication for Requests
Home-page: https://github.com/sam-washington/requests-aws4auth
Author: Sam Washington
Author-email: codegreen@aethris.net
License: MIT License
Download-URL: https://github.com/sam-washington/requests-aws4auth/tarball/0.40
Keywords: requests authentication amazon web services aws s3 REST
Platform: UNKNOWN
Classifier: Development Status :: 3 - Alpha
Classifier: Intended Audience :: Developers
Classifier: Natural Language :: English
Classifier: License :: OSI Approved :: MIT License
Classifier: Programming Language :: Python
Classifier: Programming Language :: Python :: 2
Classifier: Programming Language :: Python :: 2.7
Classifier: Programming Language :: Python :: 3
Classifier: Programming Language :: Python :: 3.3
Classifier: Programming Language :: Python :: 3.4
Classifier: Programming Language :: Python :: 3.5
Classifier: Topic :: Internet :: WWW/HTTP
